<annotation>
	<folder>images</folder>
	<filename>10320.png</filename>
	<path>/Users/i351707/Desktop/images/10320.png</path>
	<source>
		<database>Unknown</database>
	</source>
	<size>
		<width>720</width>
		<height>960</height>
		<depth>3</depth>
	</size>
	<segmented>0</segmented>
	<object>
		<name>txt</name>
		<pose>Unspecified</pose>
		<truncated>0</truncated>
		<difficult>0</difficult>
		<bndbox>
			<xmin>137</xmin>
			<ymin>195</ymin>
			<xmax>485</xmax>
			<ymax>409</ymax>
		</bndbox>
	</object>
	<object>
		<name>ba</name>
		<pose>Unspecified</pose>
		<truncated>0</truncated>
		<difficult>0</difficult>
		<bndbox>
			<xmin>199</xmin>
			<ymin>416</ymin>
			<xmax>418</xmax>
			<ymax>545</ymax>
		</bndbox>
	</object>
</annotation>